valoric/__init__.py
valoric-0.0.1.dist-info/METADATA
valoric-0.0.1.dist-info/WHEEL
valoric-0.0.1.dist-info/top_level.txt
valoric-0.0.1.dist-info/RECORD
